{
   "Published" : "2014",
   "Author" : "李劼",
   "Audio" : [
      {
         "name" : "《枭雄与士林》选读（二十六）",
         "order" : 0
      },
      {
         "order" : 1,
         "name" : "《枭雄与士林》选读（二十五）"
      },
      {
         "order" : 2,
         "name" : "《枭雄与士林》选读（二十四）"
      },
      {
         "name" : "《枭雄与士林》选读（二十三）",
         "order" : 3
      },
      {
         "order" : 4,
         "name" : "《枭雄与士林》选读（二十二）"
      },
      {
         "name" : "《枭雄与士林》选读（二十一）",
         "order" : 5
      },
      {
         "order" : 6,
         "name" : "《枭雄与士林》选读（二十）"
      },
      {
         "order" : 7,
         "name" : "《枭雄与士林》选读（十九）"
      },
      {
         "name" : "《枭雄与士林》选读（十八）",
         "order" : 8
      },
      {
         "order" : 9,
         "name" : "《枭雄与士林》选读（十七）"
      },
      {
         "name" : "《枭雄与士林》选读（十六）",
         "order" : 10
      },
      {
         "order" : 11,
         "name" : "《枭雄与士林》选读（十五）"
      },
      {
         "name" : "《枭雄与士林》选读（十四）",
         "order" : 12
      },
      {
         "order" : 13,
         "name" : "《枭雄与士林》选读（十三）"
      },
      {
         "name" : "《枭雄与士林》选读（十二）",
         "order" : 14
      },
      {
         "order" : 15,
         "name" : "《枭雄与士林》选读（十一）"
      },
      {
         "order" : 16,
         "name" : "《枭雄与士林》选读（十）"
      },
      {
         "order" : 17,
         "name" : "《枭雄与士林》选读（九）"
      },
      {
         "order" : 18,
         "name" : "《枭雄与士林》选读（八）"
      },
      {
         "name" : "《枭雄与士林》选读（七）",
         "order" : 19
      },
      {
         "order" : 20,
         "name" : "《枭雄与士林》选读（六）"
      },
      {
         "order" : 21,
         "name" : "《枭雄与士林》选读（五）"
      },
      {
         "order" : 22,
         "name" : "《枭雄与士林》选读（四）"
      },
      {
         "name" : "《枭雄与士林》选读（三）",
         "order" : 23
      },
      {
         "name" : "《枭雄与士林》选读（二）",
         "order" : 24
      },
      {
         "name" : "《枭雄与士林》选读（一）",
         "order" : 25
      }
   ]
}
